Huatuo/__init__.py
Huatuo/huatuo.py
Huatuo/data/dict/check.txt
Huatuo/data/dict/deny.txt
Huatuo/data/dict/department.txt
Huatuo/data/dict/disease.txt
Huatuo/data/dict/drug.txt
Huatuo/data/dict/food.txt
Huatuo/data/dict/physical_examination.txt
Huatuo/data/dict/producer.txt
Huatuo/data/dict/symptom.txt
Huatuo-0.1.5.dist-info/LICENSE
Huatuo-0.1.5.dist-info/METADATA
Huatuo-0.1.5.dist-info/WHEEL
Huatuo-0.1.5.dist-info/top_level.txt
Huatuo-0.1.5.dist-info/RECORD
