Metadata-Version: 2.1
Name: Huatuo
Version: 0.1.5
Summary: Provide medical NER service
Home-page: https://github.com/easonforai/Huatuo
Author: Eason Hua
Author-email: 
License: UNKNOWN
Platform: UNKNOWN
Classifier: Programming Language :: Python :: 3
Classifier: License :: OSI Approved :: MIT License
Classifier: Operating System :: OS Independent
License-File: LICENSE
Requires-Dist: tqdm (==4.62.3)
Requires-Dist: numpy (==1.21.5)
Requires-Dist: keras (==2.3.1)
Requires-Dist: tensorflow (==2.1.0)
Requires-Dist: bert4keras (==0.10.9)
Requires-Dist: pyahocorasick (==1.4.4)
